Workbook

Sheet Raw 24
A1: No | B1: SA | C1: ACC | D1: Date | E1: Description | F1: Paid in | G1: Paid out | H1: Balance | I1: NET | J1: Balance UC | K1: Check UC | L1: UC category
A2: 151 | B2: SA24 | C2: FY24 | D2: 45261 | E2: Automated Credit ICONIC EYEWE KUOONA LIMITED COM FP 30/11/23 1854 088430524581031101 | F2: 1200 | H2: 13590.3 | I2: =F2-G2 -> 1200 | J2: 13590.3 | K2: =H2-J2 -> 0 | L2: Income | M2: =VLOOKUP(A2,#REF!,6,FALSE) -> #REF!
A3: 152 | B3: SA24 | C3: FY24 | D3: 45261 | E3: Automated Credit BOOTS OPTICIANS PR 1003 2000004442 K | F3: 2500 | H3: 16090.3 | I3: =F3-G3 -> 2500 | J3: =J2+I3 -> 16090.3 | K3: =H3-J3 -> 0 | L3: Income | M3: =VLOOKUP(A3,#REF!,6,FALSE) -> #REF!
A4: 153 | B4: SA24 | C4: FY24 | D4: 45261 | E4: Direct Debit THE COLLEGE OF OPT DD001773 | G4: 25.42 | H4: 16064.88 | I4: =F4-G4 -> -25.42 | J4: =J3+I4 -> 16064.88 | K4: =H4-J4 -> 0 | L4: Professional - College | M4: =VLOOKUP(A4,#REF!,6,FALSE) -> #REF!
A5: 154 | B5: SA24 | C5: FY24 | D5: 45266 | E5: OnLine Transaction CHIDO HOVE In VIA MOBILE - LVP FP 05/12/23 10 01224352238059000N | G5: 1000 | H5: 15064.88 | I5: =F5-G5 -> -1000 | J5: =J4+I5 -> 15064.88 | K5: =H5-J5 -> 0 | L5: Dividend | M5: =VLOOKUP(A5,#REF!,6,FALSE) -> #REF!
A6: 155 | B6: SA24 | C6: FY24 | D6: 45267 | E6: Automated Credit VISION EXPRESS UK 200003317620 | F6: 850 | H6: 15914.88 | I6: =F6-G6 -> 850 | J6: =J5+I6 -> 15914.88 | K6: =H6-J6 -> 0 | L6: Income | M6: =VLOOKUP(A6,#REF!,6,FALSE) -> #REF!
A7: 156 | B7: SA24 | C7: FY24 | D7: 45268 | E7: Automated Credit SPECSAVERS FINANCE SPECSAVERS SEP COM | F7: 2400 | H7: 18314.88 | I7: =F7-G7 -> 2400 | J7: =J6+I7 -> 18314.88 | K7: =H7-J7 -> 0 | L7: Income | M7: =VLOOKUP(A7,#REF!,6,FALSE) -> #REF!
A8: 157 | B8: SA24 | C8: FY24 | D8: 45272 | E8: Automated Credit C HOVE CASH RETURN FP 11/12/23 2324 500000001255931510 | F8: 500 | H8: 18814.88 | I8: =F8-G8 -> 500 | J8: =J7+I8 -> 18814.88 | K8: =H8-J8 -> 0 | L8: Income | M8: =VLOOKUP(A8,#REF!,6,FALSE) -> #REF!
A9: 158 | B9: SA24 | C9: FY24 | D9: 45272 | E9: OnLine Transaction CHIDO HOVE INVEST VIA ONLINE - PYMT FP 11/12/23 10 36224100239120000N | G9: 5000 | H9: 13814.88 | I9: =F9-G9 -> -5000 | J9: =J8+I9 -> 13814.88 | K9: =H9-J9 -> 0 | L9: Dividend | M9: =VLOOKUP(A9,#REF!,6,FALSE) -> #REF!
A10: 159 | B10: SA24 | C10: FY24 | D10: 45280 | E10: Card Transaction 4163 19DEC23 C TAMAR BRIDGE PLYMOUTH GB | G10: 2.6 | H10: 13812.28 | I10: =F10-G10 -> -2.6 | J10: =J9+I10 -> 13812.28 | K10: =H10-J10 -> 0 | L10: Toll | M10: =VLOOKUP(A10,#REF!,6,FALSE) -> #REF!
A11: 160 | B11: SA24 | C11: FY24 | D11: 45653 | E11: OnLine Transaction CHIDO HOVE INVEST VIA MOBILE - PYMT FP 26/12/23 10 52121347307951000N | G11: 1000 | H11: 12812.28 | I11: =F11-G11 -> -1000 | J11: =J10+I11 -> 12812.28 | K11: =H11-J11 -> 0 | L11: Dividend | M11: =VLOOKUP(A11,#REF!,6,FALSE) -> #REF!
A12: 161 | B12: SA24 | C12: FY24 | D12: 45654 | E12: OnLine Transaction CHIDO HOVE TRANSFER VIA MOBILE - PYMT FP 28/12/23 10 30071348133982000N | G12: 1000 | H12: 11812.28 | I12: =F12-G12 -> -1000 | J12: =J11+I12 -> 11812.28 | K12: =H12-J12 -> 0 | L12: Dividend | M12: =VLOOKUP(A12,#REF!,6,FALSE) -> #REF!
A13: 162 | B13: SA24 | C13: FY24 | D13: 45293 | E13: OnLine Transaction CHIDO HOVE TRANSFER VIA MOBILE - PYMT FP 01/01/24 10 47215400526440000N | G13: 1000 | H13: 10812.28 | I13: =F13-G13 -> -1000 | J13: =J12+I13 -> 10812.28 | K13: =H13-J13 -> 0 | L13: Dividend | M13: =VLOOKUP(A13,#REF!,6,FALSE) -> #REF!
A14: 163 | B14: SA24 | C14: FY24 | D14: 45293 | E14: OnLine Transaction CHIDO HOVE TRANSFER VIA MOBILE - PYMT FP 30/12/23 10 59132623308479000N | G14: 1000 | H14: 9812.28 | I14: =F14-G14 -> -1000 | J14: =J13+I14 -> 9812.28 | K14: =H14-J14 -> 0 | L14: Dividend | M14: =VLOOKUP(A14,#REF!,6,FALSE) -> #REF!
A15: 164 | B15: SA24 | C15: FY24 | D15: 45293 | E15: Card Transaction 4163 30DEC23 C TESCO-STORES-6106 CALLINGTON GB | G15: 30.7 | H15: 9781.58 | I15: =F15-G15 -> -30.7 | J15: =J14+I15 -> 9781.58 | K15: =H15-J15 -> 0 | L15: Trivial | M15: =VLOOKUP(A15,#REF!,6,FALSE) -> #REF!
A16: 165 | B16: SA24 | C16: FY24 | D16: 45293 | E16: Direct Debit THE COLLEGE OF OPT DD001773 | G16: 25.42 | H16: 9756.16 | I16: =F16-G16 -> -25.42 | J16: =J15+I16 -> 9756.16 | K16: =H16-J16 -> 0 | L16: Professional - College | M16: =VLOOKUP(A16,#REF!,6,FALSE) -> #REF!
A17: 166 | B17: SA24 | C17: FY24 | D17: 45293 | E17: Direct Debit ASSOC OPTOMETRISTS 0000070593 | G17: 72 | H17: 9684.16 | I17: =F17-G17 -> -72 | J17: =J16+I17 -> 9684.16 | K17: =H17-J17 -> 0 | L17: Professional - AOP | M17: =VLOOKUP(A17,#REF!,6,FALSE) -> #REF!
A18: 167 | B18: SA24 | C18: FY24 | D18: 45296 | E18: Automated Credit SPECSAVERS FINANCE SPECSAVERS SEP COM | F18: 1600 | H18: 11284.16 | I18: =F18-G18 -> 1600 | J18: =J17+I18 -> 11284.16 | K18: =H18-J18 -> 0 | L18: Income | M18: =VLOOKUP(A18,#REF!,6,FALSE) -> #REF!
A19: 168 | B19: SA24 | C19: FY24 | D19: 45301 | E19: Automated Credit SPECSAVERS FINANCE SPECSAVERS SEP COM | F19: 2500 | H19: 13784.16 | I19: =F19-G19 -> 2500 | J19: =J18+I19 -> 13784.16 | K19: =H19-J19 -> 0 | L19: Income | M19: =VLOOKUP(A19,#REF!,6,FALSE) -> #REF!
A20: 169 | B20: SA24 | C20: FY24 | D20: 45301 | E20: Card Transaction 4163 09JAN24 C TAMAR BRIDGE PLYMOUTH GB | G20: 2.6 | H20: 13781.56 | I20: =F20-G20 -> -2.6 | J20: =J19+I20 -> 13781.56 | K20: =H20-J20 -> 0 | L20: Toll | M20: =VLOOKUP(A20,#REF!,6,FALSE) -> #REF!
A21: 170 | B21: SA24 | C21: FY24 | D21: 45303 | E21: Automated Credit LOCUM MATCH LIMITE ASDA PAYMENT FP 12/01/24 0232 05023128353259000J ASDA PAYMENT | F21: 1760 | H21: 15541.56 | I21: =F21-G21 -> 1760 | J21: =J20+I21 -> 15541.56 | K21: =H21-J21 -> 0 | L21: Income | M21: =VLOOKUP(A21,#REF!,6,FALSE) -> #REF!
A22: 171 | B22: SA24 | C22: FY24 | D22: 45303 | E22: Card Transaction 4163 11JAN24 C TAMAR BRIDGE PLYMOUTH GB | G22: 2.6 | H22: 15538.96 | I22: =F22-G22 -> -2.6 | J22: =J21+I22 -> 15538.96 | K22: =H22-J22 -> 0 | L22: Toll | M22: =VLOOKUP(A22,#REF!,6,FALSE) -> #REF!
A23: 172 | B23: SA24 | C23: FY24 | D23: 45306 | E23: OnLine Transaction CHIDO HOVE TRANSFER VIA MOBILE - | G23: 1000 | H23: 14538.96 | I23: =F23-G23 -> -1000 | J23: =J22+I23 -> 14538.96 | K23: =H23-J23 -> 0 | L23: Dividend | M23: =VLOOKUP(A23,#REF!,6,FALSE) -> #REF!
A24: 173 | B24: SA24 | C24: FY24 | D24: 45306 | E24: Card Transaction 4163 13JAN24 C TESCO-STORES-6106 | G24: 22.02 | H24: 14516.94 | I24: =F24-G24 -> -22.02 | J24: =J23+I24 -> 14516.94 | K24: =H24-J24 -> 0 | L24: Trivial | M24: =VLOOKUP(A24,#REF!,6,FALSE) -> #REF!
A25: 174 | B25: SA24 | C25: FY24 | D25: 45310 | E25: Automated Credit LOCUM MATCH LIMITE ASDA PAYMENT | F25: 440 | H25: 14956.94 | I25: =F25-G25 -> 440 | J25: =J24+I25 -> 14956.94 | K25: =H25-J25 -> 0 | L25: Income | M25: =VLOOKUP(A25,#REF!,6,FALSE) -> #REF!
A26: 175 | B26: SA24 | C26: FY24 | D26: 45310 | E26: Automated Credit SPECSAVERS FINANCE SPECSAVERS SEP | F26: 1500 | H26: 16456.94 | I26: =F26-G26 -> 1500 | J26: =J25+I26 -> 16456.94 | K26: =H26-J26 -> 0 | L26: Income | M26: =VLOOKUP(A26,#REF!,6,FALSE) -> #REF!
A27: 176 | B27: SA24 | C27: FY24 | D27: 45314 | E27: Card Transaction 4163 22JAN24 C TAMAR BRIDGE PLYMOUTH GB | G27: 2.6 | H27: 16454.34 | I27: =F27-G27 -> -2.6 | J27: =J26+I27 -> 16454.34 | K27: =H27-J27 -> 0 | L27: Toll | M27: =VLOOKUP(A27,#REF!,6,FALSE) -> #REF!
A28: 177 | B28: SA24 | C28: FY24 | D28: 45315 | E28: Card Transaction 4163 22JAN24 HTTPS://WWW .PLYMOUTH.G 01752668000 GB | G28: 2.8 | H28: 16451.54 | I28: =F28-G28 -> -2.8 | J28: =J27+I28 -> 16451.54 | K28: =H28-J28 -> 0 | L28: Parking | M28: =VLOOKUP(A28,#REF!,6,FALSE) -> #REF!
A29: 178 | B29: SA24 | C29: FY24 | D29: 45315 | E29: Automated Credit SPECSAVERS FINANCE SPECSAVERS SEP COM | F29: 399.97 | H29: 16851.51 | I29: =F29-G29 -> 399.97 | J29: =J28+I29 -> 16851.51 | K29: =H29-J29 -> 0 | L29: Income | M29: =VLOOKUP(A29,#REF!,6,FALSE) -> #REF!
A30: 179 | B30: SA24 | C30: FY24 | D30: 45316 | E30: Card Transaction 4163 23JAN24 C TAMAR BRIDGE PLYMOUTH GB | G30: 2.6 | H30: 16848.91 | I30: =F30-G30 -> -2.6 | J30: =J29+I30 -> 16848.91 | K30: =H30-J30 -> 0 | L30: Toll | M30: =VLOOKUP(A30,#REF!,6,FALSE) -> #REF!
A31: 180 | B31: SA24 | C31: FY24 | D31: 45316 | E31: Card Transaction 4163 23JAN24 C TAMAR BRIDGE PLYMOUTH GB | G31: 2.6 | H31: 16846.31 | I31: =F31-G31 -> -2.6 | J31: =J30+I31 -> 16846.31 | K31: =H31-J31 -> 0 | L31: Toll | M31: =VLOOKUP(A31,#REF!,6,FALSE) -> #REF!
A32: 181 | B32: SA24 | C32: FY24 | D32: 45320 | E32: Automated Credit ICONIC EYEWE KUOONA LIMITED COM FP 27/01/24 1359 507114009531721001 | F32: 400 | H32: 17246.31 | I32: =F32-G32 -> 400 | J32: =J31+I32 -> 17246.31 | K32: =H32-J32 -> 0 | L32: Income | M32: =VLOOKUP(A32,#REF!,6,FALSE) -> #REF!
A33: 182 | B33: SA24 | C33: FY24 | D33: 45320 | E33: OnLine Transaction CHIDO HOVE TRANSFER VIA MOBILE - PYMT FP 29/01/24 10 41083427398667000N | G33: 1000 | H33: 16246.31 | I33: =F33-G33 -> -1000 | J33: =J32+I33 -> 16246.31 | K33: =H33-J33 -> 0 | L33: Dividend | M33: =VLOOKUP(A33,#REF!,6,FALSE) -> #REF!
A34: 183 | B34: SA24 | C34: FY24 | D34: 45322 | E34: Automated Credit SPECSAVERS FINANCE SPECSAVERS SEP COM | F34: 2000 | H34: 18246.31 | I34: =F34-G34 -> 2000 | J34: =J33+I34 -> 18246.31 | K34: =H34-J34 -> 0 | L34: Income | M34: =VLOOKUP(A34,#REF!,6,FALSE) -> #REF!
A35: 184 | B35: SA24 | C35: FY24 | D35: 45323 | E35: Direct Debit THE COLLEGE OF OPT DD00177 | G35: 25.42 | H35: 18220.89 | I35: =F35-G35 -> -25.42 | J35: =J34+I35 -> 18220.89 | K35: =H35-J35 -> 0 | L35: Professional - College | M35: =VLOOKUP(A35,#REF!,6,FALSE) -> #REF!
A36: 185 | B36: SA24 | C36: FY24 | D36: 45323 | E36: Direct Debit ASSOC OPTOMETRISTS 0000070593 | G36: 72 | H36: 18148.89 | I36: =F36-G36 -> -72 | J36: =J35+I36 -> 18148.89 | K36: =H36-J36 -> 0 | L36: Professional - AOP | M36: =VLOOKUP(A36,#REF!,6,FALSE) -> #REF!
A37: 186 | B37: SA24 | C37: FY24 | D37: 45324 | E37: Automated Credit LOCUM PAYROL LTD ASDA FP 02/02/24 0427 MF06680E05C8E5B000 | F37: 880 | H37: 19028.89 | I37: =F37-G37 -> 880 | J37: =J36+I37 -> 19028.89 | K37: =H37-J37 -> 0 | L37: Income | M37: =VLOOKUP(A37,#REF!,6,FALSE) -> #REF!
A38: 187 | B38: SA24 | C38: FY24 | D38: 45324 | E38: OnLine Transaction CHIDO HOVE TRANSFER VIA ONLINE - PYMT FP 01/02/24 10 60200431240120000N | G38: 3000 | H38: 16028.89 | I38: =F38-G38 -> -3000 | J38: =J37+I38 -> 16028.89 | K38: =H38-J38 -> 0 | L38: Dividend | M38: =VLOOKUP(A38,#REF!,6,FALSE) -> #REF!
A39: 188 | B39: SA24 | C39: FY24 | D39: 45324 | E39: Card Transaction 4163 01FEB24 C TAMAR BRIDGE PLYMOUTH GB | G39: 2.6 | H39: 16026.29 | I39: =F39-G39 -> -2.6 | J39: =J38+I39 -> 16026.29 | K39: =H39-J39 -> 0 | L39: Toll | M39: =VLOOKUP(A39,#REF!,6,FALSE) -> #REF!
A40: 189 | B40: SA24 | C40: FY24 | D40: 45330 | E40: Card Transaction 4163 01FEB24 C TAMAR BRIDGE PLYMOUTH GB | G40: 2.6 | H40: 16023.69 | I40: =F40-G40 -> -2.6 | J40: =J39+I40 -> 16023.69 | K40: =H40-J40 -> 0 | L40: Toll | M40: =VLOOKUP(A40,#REF!,6,FALSE) -> #REF!
A41: 190 | B41: SA24 | C41: FY24 | D41: 45331 | E41: Automated Credit LOCUM PAYROL LTD ASDA FP 09/02/24 0426 MF06310E05D0FD1C00 | F41: 880 | H41: 16903.69 | I41: =F41-G41 -> 880 | J41: =J40+I41 -> 16903.69 | K41: =H41-J41 -> 0 | L41: Income | M41: =VLOOKUP(A41,#REF!,6,FALSE) -> #REF!
A42: 191 | B42: SA24 | C42: FY24 | D42: 45337 | E42: Automated Credit BOOTS OPTICIANS PR 1003 2000007863 K | F42: 450 | H42: 17353.69 | I42: =F42-G42 -> 450 | J42: =J41+I42 -> 17353.69 | K42: =H42-J42 -> 0 | L42: Income | M42: =VLOOKUP(A42,#REF!,6,FALSE) -> #REF!
A43: 192 | B43: SA24 | C43: FY24 | D43: 45341 | E43: OnLine Transaction CHIDO HOVE TRANSFER VIA MOBILE - PYMT FP 18/02/24 10 02024505456541000N | G43: 120 | H43: 17233.69 | I43: =F43-G43 -> -120 | J43: =J42+I43 -> 17233.69 | K43: =H43-J43 -> 0 | L43: Dividend | M43: =VLOOKUP(A43,#REF!,6,FALSE) -> #REF!
A44: 193 | B44: SA24 | C44: FY24 | D44: 45341 | E44: Card Transaction 4163 16FEB24 C TAMAR BRIDGE PLYMOUTH GB | G44: 2.6 | H44: 17231.09 | I44: =F44-G44 -> -2.6 | J44: =J43+I44 -> 17231.09 | K44: =H44-J44 -> 0 | L44: Toll | M44: =VLOOKUP(A44,#REF!,6,FALSE) -> #REF!
A45: 194 | B45: SA24 | C45: FY24 | D45: 45342 | E45: OnLine Transaction CHIDO HOVE TRANSFER VIA MOBILE - PYMT FP 20/02/24 10 60130231717931000N | G45: 5000 | H45: 12231.09 | I45: =F45-G45 -> -5000 | J45: =J44+I45 -> 12231.09 | K45: =H45-J45 -> 0 | L45: Dividend | M45: =VLOOKUP(A45,#REF!,6,FALSE) -> #REF!
A46: 195 | B46: SA24 | C46: FY24 | D46: 45345 | E46: Automated Credit SPECSAVERS FINANCE SPECSAVERS SEP COM | F46: 5500 | H46: 17731.09 | I46: =F46-G46 -> 5500 | J46: =J45+I46 -> 17731.09 | K46: =H46-J46 -> 0 | L46: Income | M46: =VLOOKUP(A46,#REF!,6,FALSE) -> #REF!
A47: 196 | B47: SA24 | C47: FY24 | D47: 45345 | E47: Card Transaction 4163 22FEB24 C TAMAR BRIDGE PLYMOUTH GB | G47: 2.6 | H47: 17728.49 | I47: =F47-G47 -> -2.6 | J47: =J46+I47 -> 17728.49 | K47: =H47-J47 -> 0 | L47: Toll | M47: =VLOOKUP(A47,#REF!,6,FALSE) -> #REF!
A48: 197 | B48: SA24 | C48: FY24 | D48: 45351 | E48: Card Transaction 4163 28FEB24 C TAMAR BRIDGE PLYMOUTH GB | G48: 2.6 | H48: 17725.89 | I48: =F48-G48 -> -2.6 | J48: =J47+I48 -> 17725.89 | K48: =H48-J48 -> 0 | L48: Toll | M48: =VLOOKUP(A48,#REF!,6,FALSE) -> #REF!
A49: 198 | B49: SA24 | C49: FY24 | D49: 45352 | E49: Automated Credit SCRIVENS LTD | F49: 495 | H49: 18220.89 | I49: =F49-G49 -> 495 | J49: =J48+I49 -> 18220.89 | K49: =H49-J49 -> 0 | L49: Income | M49: =VLOOKUP(A49,#REF!,6,FALSE) -> #REF!
A50: 199 | B50: SA24 | C50: FY24 | D50: 45352 | E50: Automated Credit SPECSAVERS FINANCE SPECSAVERS SEP COM | F50: 2500 | H50: 20720.89 | I50: =F50-G50 -> 2500 | J50: =J49+I50 -> 20720.89 | K50: =H50-J50 -> 0 | L50: Income | M50: =VLOOKUP(A50,#REF!,6,FALSE) -> #REF!
A51: 200 | B51: SA24 | C51: FY24 | D51: 45352 | E51: Automated Credit BOOTS OPTICIANS PR 1003 2000008641 K | F51: 425 | H51: 21145.89 | I51: =F51-G51 -> 425 | J51: =J50+I51 -> 21145.89 | K51: =H51-J51 -> 0 | L51: Income | M51: =VLOOKUP(A51,#REF!,6,FALSE) -> #REF!
A52: 201 | B52: SA24 | C52: FY24 | D52: 45352 | E52: Card Transaction 4163 29FEB24 C TAMAR BRIDGE PLYMOUTH GB | G52: 2.6 | H52: 21143.29 | I52: =F52-G52 -> -2.6 | J52: =J51+I52 -> 21143.29 | K52: =H52-J52 -> 0 | L52: Toll | M52: =VLOOKUP(A52,#REF!,6,FALSE) -> #REF!
A53: 202 | B53: SA24 | C53: FY24 | D53: 45352 | E53: Direct Debit THE COLLEGE OF OPT DD001773 | G53: 25.42 | H53: 21117.87 | I53: =F53-G53 -> -25.42 | J53: =J52+I53 -> 21117.87 | K53: =H53-J53 -> 0 | L53: Professional - College | M53: =VLOOKUP(A53,#REF!,6,FALSE) -> #REF!
A54: 203 | B54: SA24 | C54: FY24 | D54: 45352 | E54: Direct Debit ASSOC OPTOMETRISTS 0000070593 | G54: 72 | H54: 21045.87 | I54: =F54-G54 -> -72 | J54: =J53+I54 -> 21045.87 | K54: =H54-J54 -> 0 | L54: Professional - AOP | M54: =VLOOKUP(A54,#REF!,6,FALSE) -> #REF!
A55: 204 | B55: SA24 | C55: FY24 | D55: 45356 | E55: Card Transaction 4163 04MAR24 EB *DEVON LOC STUDY DA 801-413-7200 GB | G55: 35 | H55: 21010.87 | I55: =F55-G55 -> -35 | J55: =J54+I55 -> 21010.87 | K55: =H55-J55 -> 0 | L55: Training | M55: =VLOOKUP(A55,#REF!,6,FALSE) -> #REF!
A56: 205 | B56: SA24 | C56: FY24 | D56: 45356 | E56: Card Transaction 4163 04MAR24 WWW.OPTICAL.ORG LONDON GB | G56: 405 | H56: 20605.87 | I56: =F56-G56 -> -405 | J56: =J55+I56 -> 20605.87 | K56: =H56-J56 -> 0 | L56: Professional Fee | M56: =VLOOKUP(A56,#REF!,6,FALSE) -> #REF!
A57: 206 | B57: SA24 | C57: FY24 | D57: 45357 | E57: Automated Credit SPECSAVERS FINANCE SPECSAVERS SEP COM | F57: 1000 | H57: 21605.87 | I57: =F57-G57 -> 1000 | J57: =J56+I57 -> 21605.87 | K57: =H57-J57 -> 0 | L57: Income | M57: =VLOOKUP(A57,#REF!,6,FALSE) -> #REF!
A58: 207 | B58: SA24 | C58: FY24 | D58: 45364 | E58: Card Transaction 4163 12MAR24 C TAMAR BRIDGE PLYMOUTH GB | G58: 2.6 | H58: 21603.27 | I58: =F58-G58 -> -2.6 | J58: =J57+I58 -> 21603.27 | K58: =H58-J58 -> 0 | L58: Toll | M58: =VLOOKUP(A58,#REF!,6,FALSE) -> #REF!
A59: 208 | B59: SA24 | C59: FY24 | D59: 45365 | E59: Automated Credit SPECSAVERS FINANCE SPECSAVERS SEP COM | F59: 800 | H59: 22403.27 | I59: =F59-G59 -> 800 | J59: =J58+I59 -> 22403.27 | K59: =H59-J59 -> 0 | L59: Income | M59: =VLOOKUP(A59,#REF!,6,FALSE) -> #REF!
A60: 209 | B60: SA24 | C60: FY24 | D60: 45365 | E60: Card Transaction 4163 13MAR24 C TAMAR BRIDGE PLYMOUTH GB | G60: 2.6 | H60: 22400.67 | I60: =F60-G60 -> -2.6 | J60: =J59+I60 -> 22400.67 | K60: =H60-J60 -> 0 | L60: Toll | M60: =VLOOKUP(A60,#REF!,6,FALSE) -> #REF!
A61: 210 | B61: SA24 | C61: FY24 | D61: 45366 | E61: Automated Credit LOCUM PAYROL LTD ASDA FP 15/03/24 0443 MF074714400E1B3D00 | F61: 2200 | H61: 24600.67 | I61: =F61-G61 -> 2200 | J61: =J60+I61 -> 24600.67 | K61: =H61-J61 -> 0 | L61: Income | M61: =VLOOKUP(A61,#REF!,6,FALSE) -> #REF!
A62: 211 | B62: SA24 | C62: FY24 | D62: 45366 | E62: OnLine Transaction CHIDO HOVE TRANSFER VIA MOBILE - PYMT FP 15/03/24 10 29161216081850000N | G62: 300 | H62: 24300.67 | I62: =F62-G62 -> -300 | J62: =J61+I62 -> 24300.67 | K62: =H62-J62 -> 0 | L62: Dividend | M62: =VLOOKUP(A62,#REF!,6,FALSE) -> #REF!
A63: 212 | B63: SA24 | C63: FY24 | D63: 45366 | E63: Card Transaction 4163 14MAR24 C TAMAR BRIDGE PLYMOUTH GB | G63: 2.6 | H63: 24298.07 | I63: =F63-G63 -> -2.6 | J63: =J62+I63 -> 24298.07 | K63: =H63-J63 -> 0 | L63: Toll | M63: =VLOOKUP(A63,#REF!,6,FALSE) -> #REF!
A64: 213 | B64: SA24 | C64: FY24 | D64: 45369 | E64: Card Transaction 4163 15MAR24 EURO CAR PARKS LTD LONDON GB | G64: 50 | H64: 24248.07 | I64: =F64-G64 -> -50 | J64: =J63+I64 -> 24248.07 | K64: =H64-J64 -> 0 | L64: Parking | M64: =VLOOKUP(A64,#REF!,6,FALSE) -> #REF!
A65: 214 | B65: SA24 | C65: FY24 | D65: 45370 | E65: OnLine Transaction CHIDO HOVE TRANSFER VIA MOBILE - PYMT FP 19/03/24 10 55152550137006000N | G65: 4500 | H65: 19748.07 | I65: =F65-G65 -> -4500 | J65: =J64+I65 -> 19748.07 | K65: =H65-J65 -> 0 | L65: Dividend | M65: =VLOOKUP(A65,#REF!,6,FALSE) -> #REF!
A66: 215 | B66: SA24 | C66: FY24 | D66: 45370 | E66: Card Transaction 4163 18MAR24 C COSTERO LOUNGE PAIGNTON GB | G66: 16.3 | H66: 19731.77 | I66: =F66-G66 -> -16.3 | J66: =J65+I66 -> 19731.77 | K66: =H66-J66 -> 0 | L66: Dinner | M66: =VLOOKUP(A66,#REF!,6,FALSE) -> #REF!
A67: 216 | B67: SA24 | C67: FY24 | D67: 45370 | E67: Card Transaction 4163 18MAR24 C TAMAR BRIDGE PLYMOUTH GB | G67: 2.6 | H67: 19729.17 | I67: =F67-G67 -> -2.6 | J67: =J66+I67 -> 19729.17 | K67: =H67-J67 -> 0 | L67: Toll | M67: =VLOOKUP(A67,#REF!,6,FALSE) -> #REF!
A68: 217 | B68: SA24 | C68: FY24 | D68: 45378 | E68: Automated Credit SPECSAVERS FINANCE SPECSAVERS SEP COM | F68: 2250 | H68: 21979.17 | I68: =F68-G68 -> 2250 | J68: =J67+I68 -> 21979.17 | K68: =H68-J68 -> 0 | L68: Income | M68: =VLOOKUP(A68,#REF!,6,FALSE) -> #REF!
A69: 218 | B69: SA24 | C69: FY24 | D69: 45378 | E69: Card Transaction 4163 26MAR24 PLYMOUTH CITY COUN PLYMOUTH GB | G69: 25 | H69: 21954.17 | I69: =F69-G69 -> -25 | J69: =J68+I69 -> 21954.17 | K69: =H69-J69 -> 0 | L69: Parking | M69: =VLOOKUP(A69,#REF!,6,FALSE) -> #REF!
A70: 219 | B70: SA24 | C70: FY24 | D70: 45384 | E70: Automated Credit LOCUM PAYROL LTD ASDA FP 29/03/24 0324 MF06941440227AC400 | F70: 440 | H70: 22394.17 | I70: =F70-G70 -> 440 | J70: =J69+I70 -> 22394.17 | K70: =H70-J70 -> 0 | L70: Income | M70: =VLOOKUP(A70,#REF!,6,FALSE) -> #REF!
A71: 220 | B71: SA24 | C71: FY24 | D71: 45384 | E71: Automated Credit BOOTS OPTICIANS PR 1003 2000010225 K | F71: 1350 | H71: 23744.17 | I71: =F71-G71 -> 1350 | J71: =J70+I71 -> 23744.17 | K71: =H71-J71 -> 0 | L71: Income | M71: =VLOOKUP(A71,#REF!,6,FALSE) -> #REF!
A72: 221 | B72: SA24 | C72: FY24 | D72: 45384 | E72: Card Transaction 4163 01APR24 C IBIS STYLE HOTEL PAIGNTON GB | G72: 16 | H72: 23728.17 | I72: =F72-G72 -> -16 | J72: =J71+I72 -> 23728.17 | K72: =H72-J72 -> 0 | L72: Hotel | M72: =VLOOKUP(A72,#REF!,6,FALSE) -> #REF!
A73: 222 | B73: SA24 | C73: FY24 | D73: 45384 | E73: Card Transaction 4163 01APR24 C TAMAR BRIDGE PLYMOUTH GB | G73: 2.6 | H73: 23725.57 | I73: =F73-G73 -> -2.6 | J73: =J72+I73 -> 23725.57 | K73: =H73-J73 -> 0 | L73: Toll | M73: =VLOOKUP(A73,#REF!,6,FALSE) -> #REF!
A74: 223 | B74: SA24 | C74: FY24 | D74: 45384 | E74: Card Transaction 4163 30MAR24 TORBAY COUNCIL - WEB TORQUAY GB | G74: 25 | H74: 23700.57 | I74: =F74-G74 -> -25 | J74: =J73+I74 -> 23700.57 | K74: =H74-J74 -> 0 | L74: Penalty | M74: =VLOOKUP(A74,#REF!,6,FALSE) -> #REF!
A75: 224 | B75: SA24 | C75: FY24 | D75: 45384 | E75: Card Transaction 4163 29MAR24 ALIEXPRESS.COM LONDON GB | G75: 30.46 | H75: 23670.11 | I75: =F75-G75 -> -30.46 | J75: =J74+I75 -> 23670.11 | K75: =H75-J75 -> 0 | L75: Equipment | M75: =VLOOKUP(A75,#REF!,6,FALSE) -> #REF!
A76: 225 | B76: SA24 | C76: FY24 | D76: 45384 | E76: Card Transaction 4163 29MAR24 BIRMINGHAM OPTICAL BIRMINGHAM GB | G76: 132 | H76: 23538.11 | I76: =F76-G76 -> -132 | J76: =J75+I76 -> 23538.11 | K76: =H76-J76 -> 0 | L76: Equipment | M76: =VLOOKUP(A76,#REF!,6,FALSE) -> #REF!
A77: 226 | B77: SA24 | C77: FY24 | D77: 45384 | E77: Direct Debit THE COLLEGE OF OPT DD001773 | G77: 25.42 | H77: 23512.69 | I77: =F77-G77 -> -25.42 | J77: =J76+I77 -> 23512.69 | K77: =H77-J77 -> 0 | L77: Professional - College | M77: =VLOOKUP(A77,#REF!,6,FALSE) -> #REF!
A78: 227 | B78: SA24 | C78: FY24 | D78: 45385 | E78: Card Transaction 4163 02APR24 C TESCO-STORES 4898 PAIGNTON GB | G78: 3 | H78: 23509.69 | I78: =F78-G78 -> -3 | J78: =J77+I78 -> 23509.69 | K78: =H78-J78 -> 0 | L78: Lunch | M78: =VLOOKUP(A78,#REF!,6,FALSE) -> #REF!
A79: 228 | B79: SA24 | C79: FY24 | D79: 45385 | E79: Card Transaction 4163 01APR24 IBIS STYLES HOTEL PAIG PAIGNTON GB | G79: 70.89 | H79: 23438.8 | I79: =F79-G79 -> -70.89 | J79: =J78+I79 -> 23438.8 | K79: =H79-J79 -> 0 | L79: Hotel | M79: =VLOOKUP(A79,#REF!,6,FALSE) -> #REF!
A80: 229 | B80: SA24 | C80: FY24 | D80: 45385 | E80: Direct Debit ASSOC OPTOMETRISTS 0000070593 | G80: 72 | H80: 23366.8 | I80: =F80-G80 -> -72 | J80: =J79+I80 -> 23366.8 | K80: =H80-J80 -> 0 | L80: Professional - AOP | M80: =VLOOKUP(A80,#REF!,6,FALSE) -> #REF!
A81: 230 | B81: SA24 | C81: FY24 | D81: 45386 | E81: Card Transaction 4163 03APR24 C CORNWALL COUNCIL - MO TRURO GB | G81: 10.5 | H81: 23356.3 | I81: =F81-G81 -> -10.5 | J81: =J80+I81 -> 23356.3 | K81: =H81-J81 -> 0 | L81: Parking | M81: =VLOOKUP(A81,#REF!,6,FALSE) -> #REF!
A82: 231 | B82: SA24 | C82: FY24 | D82: 45387 | E82: Automated Credit SPECSAVERS FINANCE SPECSAVERS SEP COM | F82: 800 | H82: 24156.3 | I82: =F82-G82 -> 800 | J82: =J81+I82 -> 24156.3 | K82: =H82-J82 -> 0 | L82: Income | M82: =VLOOKUP(A82,#REF!,6,FALSE) -> #REF!
A83: 232 | B83: SA24 | C83: FY24 | D83: 45387 | E83: Card Transaction 4163 04APR24 C TAMAR BRIDGE PLYMOUTH GB | G83: 2.6 | H83: 24153.7 | I83: =F83-G83 -> -2.6 | J83: =J82+I83 -> 24153.7 | K83: =H83-J83 -> 0 | L83: Toll | M83: =VLOOKUP(A83,#REF!,6,FALSE) -> #REF!
A84: 233 | B84: SA25 | C84: FY24 | D84: 45390 | E84: OnLine Transaction CHIDO HOVE INVEST VIA MOBILE - PYMT FP 08/04/24 10 51130224856545000N | G84: 1500 | H84: 22653.7 | I84: =F84-G84 -> -1500 | J84: =J83+I84 -> 22653.7 | K84: =H84-J84 -> 0 | L84: Dividend | M84: =VLOOKUP(A84,#REF!,6,FALSE) -> #REF!
A85: 234 | B85: SA25 | C85: FY24 | D85: 45390 | E85: OnLine Transaction CHIDO HOVE TRANSFER VIA MOBILE - PYMT FP 08/04/24 10 43130253344082000N | G85: 3500 | H85: 19153.7 | I85: =F85-G85 -> -3500 | J85: =J84+I85 -> 19153.7 | K85: =H85-J85 -> 0 | L85: Dividend | M85: =VLOOKUP(A85,#REF!,6,FALSE) -> #REF!
A86: 235 | B86: SA25 | C86: FY24 | D86: 45390 | E86: Card Transaction 4163 05APR24 C CORNWALL COUNCIL - MO TRURO GB | G86: 10.5 | H86: 19143.2 | I86: =F86-G86 -> -10.5 | J86: =J85+I86 -> 19143.2 | K86: =H86-J86 -> 0 | L86: Parking | M86: =VLOOKUP(A86,#REF!,6,FALSE) -> #REF!
A87: 236 | B87: SA25 | C87: FY24 | D87: 45391 | E87: Card Transaction 4163 08APR24 C TAMAR BRIDGE PLYMOUTH GB | G87: 2.6 | H87: 19140.6 | I87: =F87-G87 -> -2.6 | J87: =J86+I87 -> 19140.6 | K87: =H87-J87 -> 0 | L87: Toll | M87: =VLOOKUP(A87,#REF!,6,FALSE) -> #REF!
A88: 237 | B88: SA25 | C88: FY24 | D88: 45392 | E88: Card Transaction 4163 09APR24 C CORNWALL COUNCIL - MO TRURO GB | G88: 10.5 | H88: 19130.1 | I88: =F88-G88 -> -10.5 | J88: =J87+I88 -> 19130.1 | K88: =H88-J88 -> 0 | L88: Parking | M88: =VLOOKUP(A88,#REF!,6,FALSE) -> #REF!
A89: 238 | B89: SA25 | C89: FY24 | D89: 45393 | E89: Card Transaction 4163 10APR24 C TAMAR BRIDGE PLYMOUTH GB | G89: 2.6 | H89: 19127.5 | I89: =F89-G89 -> -2.6 | J89: =J88+I89 -> 19127.5 | K89: =H89-J89 -> 0 | L89: Toll | M89: =VLOOKUP(A89,#REF!,6,FALSE) -> #REF!
A90: 239 | B90: SA25 | C90: FY24 | D90: 45394 | E90: Card Transaction 4163 11APR24 C TAMAR BRIDGE PLYMOUTH GB | G90: 2.6 | H90: 19124.9 | I90: =F90-G90 -> -2.6 | J90: =J89+I90 -> 19124.9 | K90: =H90-J90 -> 0 | L90: Toll | M90: =VLOOKUP(A90,#REF!,6,FALSE) -> #REF!
A91: 240 | B91: SA25 | C91: FY24 | D91: 45397 | E91: Automated Credit BOOTS OPTICIANS PR 1003 2000011048 K | F91: 1350 | H91: 20474.9 | I91: =F91-G91 -> 1350 | J91: =J90+I91 -> 20474.9 | K91: =H91-J91 -> 0 | L91: Income | M91: =VLOOKUP(A91,#REF!,6,FALSE) -> #REF!
A92: 241 | B92: SA25 | C92: FY24 | D92: 45397 | E92: Card Transaction 4163 12APR24 C TAMAR BRIDGE PLYMOUTH GB | G92: 2.6 | H92: 20472.3 | I92: =F92-G92 -> -2.6 | J92: =J91+I92 -> 20472.3 | K92: =H92-J92 -> -2.910383e-11 | L92: Toll | M92: =VLOOKUP(A92,#REF!,6,FALSE) -> #REF!
A93: 242 | B93: SA25 | C93: FY24 | D93: 45397 | E93: Card Transaction 4163 13APR24 C GDK PLYMOUTH PLYMOUTH PL1 GB | G93: 1.43 | H93: 20470.87 | I93: =F93-G93 -> -1.43 | J93: =J92+I93 -> 20470.87 | K93: =H93-J93 -> -2.910383e-11 | L93: Lunch | M93: =VLOOKUP(A93,#REF!,6,FALSE) -> #REF!
A94: 243 | B94: SA25 | C94: FY24 | D94: 45401 | E94: Automated Credit VISION EXPRESS UK RG50570000589024 | F94: 1245 | H94: 21715.87 | I94: =F94-G94 -> 1245 | J94: =J93+I94 -> 21715.87 | K94: =H94-J94 -> -2.910383e-11 | L94: Income | M94: =VLOOKUP(A94,#REF!,6,FALSE) -> #REF!
A95: 244 | B95: SA25 | C95: FY24 | D95: 45401 | E95: Automated Credit SPECSAVERS FINANCE SPECSAVERS SEP COM | F95: 2500 | H95: 24215.87 | I95: =F95-G95 -> 2500 | J95: =J94+I95 -> 24215.87 | K95: =H95-J95 -> -2.910383e-11 | L95: Income | M95: =VLOOKUP(A95,#REF!,6,FALSE) -> #REF!
A96: 245 | B96: SA25 | C96: FY24 | D96: 45401 | E96: OnLine Transaction CHIDO HOVE TRANSFER VIA MOBILE - PYMT FP 19/04/24 10 14065550118196000N | G96: 5000 | H96: 19215.87 | I96: =F96-G96 -> -5000 | J96: =J95+I96 -> 19215.87 | K96: =H96-J96 -> -2.910383e-11 | L96: Dividend | M96: =VLOOKUP(A96,#REF!,6,FALSE) -> #REF!
A97: 246 | B97: SA25 | C97: FY24 | D97: 45413 | E97: Direct Debit THE COLLEGE OF OPT DD001773 | G97: 25.42 | H97: 19190.45 | I97: =F97-G97 -> -25.42 | J97: =J96+I97 -> 19190.45 | K97: =H97-J97 -> -2.910383e-11 | L97: Professional - College | M97: =VLOOKUP(A97,#REF!,6,FALSE) -> #REF!
A98: 247 | B98: SA25 | C98: FY24 | D98: 45413 | E98: Direct Debit ASSOCIATION OF OPT 0000070593 | G98: 72 | H98: 19118.45 | I98: =F98-G98 -> -72 | J98: =J97+I98 -> 19118.45 | K98: =H98-J98 -> -2.910383e-11 | L98: Professional - AOP | M98: =VLOOKUP(A98,#REF!,6,FALSE) -> #REF!
A99: 248 | B99: SA25 | C99: FY24 | D99: 45414 | E99: Card Transaction 4163 01MAY24 1STFORMATIO NS.CO.UK LONDON GB | G99: 0.6 | H99: 19117.85 | I99: =F99-G99 -> -0.6 | J99: =J98+I99 -> 19117.85 | K99: =H99-J99 -> -3.2741809e-11 | L99: Subscription | M99: =VLOOKUP(A99,#REF!,6,FALSE) -> #REF!
A100: 249 | B100: SA25 | C100: FY24 | D100: 45420 | E100: Card Transaction 4163 07MAY24 C TAMAR BRIDGE PLYMOUTH GB | G100: 2.6 | H100: 19115.25 | I100: =F100-G100 -> -2.6 | J100: =J99+I100 -> 19115.25 | K100: =H100-J100 -> -3.2741809e-11 | L100: Toll | M100: =VLOOKUP(A100,#REF!,6,FALSE) -> #REF!
...

Sheet Analysis 24
A3: Sum of NET | B3: Column Labels
A4: Row Labels | B4: FY24 | C4: FY25
A5: AOP | B5: =SUMIFS('Raw 24'!$I:$I,'Raw 24'!$C:$C,$B$4,'Raw 24'!$L:$L,$A5) -> 0 | C5: =SUMIFS('Raw 24'!$I:$I,'Raw 24'!$C:$C,$C$4,'Raw 24'!$L:$L,$A5) -> -86.16
A6: Accountancy | B6: =SUMIFS('Raw 24'!$I:$I,'Raw 24'!$C:$C,$B$4,'Raw 24'!$L:$L,$A6) -> -613 | C6: =SUMIFS('Raw 24'!$I:$I,'Raw 24'!$C:$C,$C$4,'Raw 24'!$L:$L,$A6) -> 0
A7: Bank charges | B7: =SUMIFS('Raw 24'!$I:$I,'Raw 24'!$C:$C,$B$4,'Raw 24'!$L:$L,$A7) -> -32.9 | C7: =SUMIFS('Raw 24'!$I:$I,'Raw 24'!$C:$C,$C$4,'Raw 24'!$L:$L,$A7) -> -9.1
A8: DLA | B8: =SUMIFS('Raw 24'!$I:$I,'Raw 24'!$C:$C,$B$4,'Raw 24'!$L:$L,$A8) -> -76.28 | C8: =SUMIFS('Raw 24'!$I:$I,'Raw 24'!$C:$C,$C$4,'Raw 24'!$L:$L,$A8) -> 0
A9: Dinner | B9: =SUMIFS('Raw 24'!$I:$I,'Raw 24'!$C:$C,$B$4,'Raw 24'!$L:$L,$A9) -> -54.45 | C9: =SUMIFS('Raw 24'!$I:$I,'Raw 24'!$C:$C,$C$4,'Raw 24'!$L:$L,$A9) -> 0
A10: Dividend | B10: =SUMIFS('Raw 24'!$I:$I,'Raw 24'!$C:$C,$B$4,'Raw 24'!$L:$L,$A10) -> -60053.41 | C10: =SUMIFS('Raw 24'!$I:$I,'Raw 24'!$C:$C,$C$4,'Raw 24'!$L:$L,$A10) -> -5000
A11: Entertainment | B11: =SUMIFS('Raw 24'!$I:$I,'Raw 24'!$C:$C,$B$4,'Raw 24'!$L:$L,$A11) -> 0 | C11: =SUMIFS('Raw 24'!$I:$I,'Raw 24'!$C:$C,$C$4,'Raw 24'!$L:$L,$A11) -> -7.5
A12: Equipment | B12: =SUMIFS('Raw 24'!$I:$I,'Raw 24'!$C:$C,$B$4,'Raw 24'!$L:$L,$A12) -> -195.28 | C12: =SUMIFS('Raw 24'!$I:$I,'Raw 24'!$C:$C,$C$4,'Raw 24'!$L:$L,$A12) -> 0
A13: HMRC | B13: =SUMIFS('Raw 24'!$I:$I,'Raw 24'!$C:$C,$B$4,'Raw 24'!$L:$L,$A13) -> 7671.08 | C13: =SUMIFS('Raw 24'!$I:$I,'Raw 24'!$C:$C,$C$4,'Raw 24'!$L:$L,$A13) -> 0
A14: HMRC CT | B14: =SUMIFS('Raw 24'!$I:$I,'Raw 24'!$C:$C,$B$4,'Raw 24'!$L:$L,$A14) -> 0 | C14: =SUMIFS('Raw 24'!$I:$I,'Raw 24'!$C:$C,$C$4,'Raw 24'!$L:$L,$A14) -> -15587.61
A15: HMRC SA | B15: =SUMIFS('Raw 24'!$I:$I,'Raw 24'!$C:$C,$B$4,'Raw 24'!$L:$L,$A15) -> -4506.33 | C15: =SUMIFS('Raw 24'!$I:$I,'Raw 24'!$C:$C,$C$4,'Raw 24'!$L:$L,$A15) -> 0
A16: HMRC-CT | B16: =SUMIFS('Raw 24'!$I:$I,'Raw 24'!$C:$C,$B$4,'Raw 24'!$L:$L,$A16) -> -8287.99 | C16: =SUMIFS('Raw 24'!$I:$I,'Raw 24'!$C:$C,$C$4,'Raw 24'!$L:$L,$A16) -> 0
... A33: Trivial | B33: =SUMIFS('Raw 24'!$I:$I,'Raw 24'!$C:$C,$B$4,'Raw 24'!$L:$L,$A33) -> -52.72 | C33: =SUMIFS('Raw 24'!$I:$I,'Raw 24'!$C:$C,$C$4,'Raw 24'!$L:$L,$A33) -> 0
A34: Grand Total | B34: =SUM(B5:B33) -> 15095.7 | C34: =SUM(C5:C33) -> -25509.53
