Workbook

Sheet RAW 2025
A1: No | B1: SA | C1: FY | D1: Date | E1: Counter Party | F1: Reference | G1: Type | H1: Amount (GBP) | I1: IN | J1: OUT | K1: Balance (GBP) | L1: Net | M1: Balance UC | N1: Check | O1: Spending Category | P1: UC Category
K2: 13312.51
A3: 1 | B3: SA24/25 | C3: FY25 | D3: 45384 | E3: Barclays Current | F3: 208813 93228126 | G3: FASTER PAYMENT | H3: -700 | J3: =IF(H3<0,H3,"") -> -700 | K3: 12612.51 | L3: =I3+J3 -> -700 | M3: =K2+L3 -> 12612.51 | N3: =K3-M3 -> 0 | O3: DIRECTORS_WAGES | P3: Directors salary
A4: 2 | B4: SA24/25 | C4: FY25 | D4: 45384 | E4: M Carlin | F4: ACCOUNTS | G4: FASTER PAYMENT | H4: -40 | J4: =IF(H4<0,H4,"") -> -40 | K4: 12572.51 | L4: =I4+J4 -> -40 | M4: =K3+L4 -> 12572.51 | N4: =K4-M4 -> 0 | O4: OTHER | P4: Accountancy fee
A5: 3 | B5: SA24/25 | C5: FY25 | D5: 45385 | E5: Association Of Optometrists | F5: 87201 | G5: DIRECT DEBIT | H5: -72 | J5: =IF(H5<0,H5,"") -> -72 | K5: 12500.51 | L5: =I5+J5 -> -72 | M5: =K4+L5 -> 12500.51 | N5: =K5-M5 -> 0 | O5: PROFESSIONAL_SERVICES | P5: AOP
A6: 4 | B6: SA24/25 | C6: FY25 | D6: 45386 | E6: Lser Connect Ecom | F6: LSER CONNECT ECOM | G6: APPLE PAY | H6: -6.9 | J6: =IF(H6<0,H6,"") -> -6.9 | K6: 12493.61 | L6: =I6+J6 -> -6.9 | M6: =K5+L6 -> 12493.61 | N6: =K6-M6 -> 0 | O6: TRAVEL | P6: Travel
A7: 5 | B7: SA24/25 | C7: FY25 | D7: 45387 | E7: Specsavers | F7: SPECSAVERS SEP COM | G7: DIRECT CREDIT | H7: 850 | I7: =IF(H7>0,H7,"") -> 850 | K7: 13343.61 | L7: =I7+J7 -> 850 | M7: =K6+L7 -> 13343.61 | N7: =K7-M7 -> 0 | O7: REVENUE | P7: Income
A8: 6 | B8: SA24/25 | C8: FY25 | D8: 45390 | E8: Barclays Current | F8: Dividend | G8: FASTER PAYMENT | H8: -3500 | J8: =IF(H8<0,H8,"") -> -3500 | K8: 9843.61 | L8: =I8+J8 -> -3500 | M8: =K7+L8 -> 9843.61 | N8: =K8-M8 -> 0 | O8: DIVIDENDS | P8: Dividends
A9: 7 | B9: SA24/25 | C9: FY25 | D9: 45392 | E9: Specsavers | F9: SPECSAVERS SEP COM | G9: DIRECT CREDIT | H9: 2825 | I9: =IF(H9>0,H9,"") -> 2825 | K9: 12668.61 | L9: =I9+J9 -> 2825 | M9: =K8+L9 -> 12668.61 | N9: =K9-M9 -> 0 | O9: REVENUE | P9: Income
A10: 8 | B10: SA24/25 | C10: FY25 | D10: 45394 | E10: Finch House Cafe | F10: Finch House Cafe | G10: APPLE PAY | H10: -11.15 | J10: =IF(H10<0,H10,"") -> -11.15 | K10: 12657.46 | L10: =I10+J10 -> -11.15 | M10: =K9+L10 -> 12657.46 | N10: =K10-M10 -> 0 | O10: FOOD_AND_DRINK | P10: Lunch
A11: 9 | B11: SA24/25 | C11: FY25 | D11: 45399 | E11: Specsavers | F11: SPECSAVERS SEP COM | G11: DIRECT CREDIT | H11: 2550 | I11: =IF(H11>0,H11,"") -> 2550 | K11: 15207.46 | L11: =I11+J11 -> 2550 | M11: =K10+L11 -> 15207.46 | N11: =K11-M11 -> 0 | O11: REVENUE | P11: Income
A12: 10 | B12: SA24/25 | C12: FY25 | D12: 45406 | E12: Specsavers | F12: SPECSAVERS SEP COM | G12: DIRECT CREDIT | H12: 425 | I12: =IF(H12>0,H12,"") -> 425 | K12: 15632.46 | L12: =I12+J12 -> 425 | M12: =K11+L12 -> 15632.46 | N12: =K12-M12 -> 0 | O12: REVENUE | P12: Income
A13: 11 | B13: SA24/25 | C13: FY25 | D13: 45407 | E13: Redwood | F13: REDWOOD | G13: APPLE PAY | H13: -13.8 | J13: =IF(H13<0,H13,"") -> -13.8 | K13: 15618.66 | L13: =I13+J13 -> -13.8 | M13: =K12+L13 -> 15618.66 | N13: =K13-M13 -> 0 | O13: FOOD_AND_DRINK | P13: Lunch
A14: 12 | B14: SA24/25 | C14: FY25 | D14: 45407 | E14: Redwood | F14: REDWOOD | G14: APPLE PAY | H14: -6.9 | J14: =IF(H14<0,H14,"") -> -6.9 | K14: 15611.76 | L14: =I14+J14 -> -6.9 | M14: =K13+L14 -> 15611.76 | N14: =K14-M14 -> 0 | O14: FOOD_AND_DRINK | P14: Lunch
A15: 13 | B15: SA24/25 | C15: FY25 | D15: 45407 | E15: TfL | F15: TFL TRAVEL CH | G15: APPLE PAY | H15: -8.4 | J15: =IF(H15<0,H15,"") -> -8.4 | K15: 15603.36 | L15: =I15+J15 -> -8.4 | M15: =K14+L15 -> 15603.36 | N15: =K15-M15 -> 0 | O15: TRAVEL | P15: Travel
A16: 14 | B16: SA24/25 | C16: FY25 | D16: 45408 | E16: Bexley Ringo Ecom | F16: BEXLEY RINGO ECOM | G16: APPLE PAY | H16: -1.7 | J16: =IF(H16<0,H16,"") -> -1.7 | K16: 15601.66 | L16: =I16+J16 -> -1.7 | M16: =K15+L16 -> 15601.66 | N16: =K16-M16 -> 0 | O16: TRAVEL | P16: Travel
A17: 15 | B17: SA24/25 | C17: FY25 | D17: 45409 | E17: LOOKING GOOD OPTICIANS LIMITED T AS | F17: wadhurst | G17: FASTER PAYMENT | H17: 700 | I17: =IF(H17>0,H17,"") -> 700 | K17: 16301.66 | L17: =I17+J17 -> 700 | M17: =K16+L17 -> 16301.66 | N17: =K17-M17 -> 0 | O17: REVENUE | P17: Income
A18: 16 | B18: SA24/25 | C18: FY25 | D18: 45413 | E18: Association Of Optometrists | F18: 87201 | G18: DIRECT DEBIT | H18: -72 | J18: =IF(H18<0,H18,"") -> -72 | K18: 16229.66 | L18: =I18+J18 -> -72 | M18: =K17+L18 -> 16229.66 | N18: =K18-M18 -> 0 | O18: PROFESSIONAL_SERVICES | P18: AOP
A19: 17 | B19: SA24/25 | C19: FY25 | D19: 45413 | E19: Barclays Current | F19: 208813 93228126 | G19: FASTER PAYMENT | H19: -700 | J19: =IF(H19<0,H19,"") -> -700 | K19: 15529.66 | L19: =I19+J19 -> -700 | M19: =K18+L19 -> 15529.66 | N19: =K19-M19 -> 0 | O19: DIRECTORS_WAGES | P19: Directors salary
A20: 18 | B20: SA24/25 | C20: FY25 | D20: 45413 | E20: M Carlin | F20: ACCOUNTS | G20: FASTER PAYMENT | H20: -40 | J20: =IF(H20<0,H20,"") -> -40 | K20: 15489.66 | L20: =I20+J20 -> -40 | M20: =K19+L20 -> 15489.66 | N20: =K20-M20 -> 0 | O20: PROFESSIONAL_SERVICES | P20: Accountancy fee
A21: 19 | B21: SA24/25 | C21: FY25 | D21: 45419 | E21: Barclays Current | F21: Dividend | G21: FASTER PAYMENT | H21: -4000 | J21: =IF(H21<0,H21,"") -> -4000 | K21: 11489.66 | L21: =I21+J21 -> -4000 | M21: =K20+L21 -> 11489.66 | N21: =K21-M21 -> 0 | O21: DIVIDENDS | P21: Dividends
A22: 20 | B22: SA24/25 | C22: FY25 | D22: 45422 | E22: Specsavers | F22: SPECSAVERS SEP COM | G22: DIRECT CREDIT | H22: 1225 | I22: =IF(H22>0,H22,"") -> 1225 | K22: 12714.66 | L22: =I22+J22 -> 1225 | M22: =K21+L22 -> 12714.66 | N22: =K22-M22 -> 0 | O22: REVENUE | P22: Income
A23: 21 | B23: SA24/25 | C23: FY25 | D23: 45426 | E23: RingGo | F23: RINGGO PARKING | G23: APPLE PAY | H23: -7 | J23: =IF(H23<0,H23,"") -> -7 | K23: 12707.66 | L23: =I23+J23 -> -7 | M23: =K22+L23 -> 12707.66 | N23: =K23-M23 -> 0 | O23: TRAVEL | P23: Travel
A24: 22 | B24: SA24/25 | C24: FY25 | D24: 45427 | E24: Specsavers | F24: SPECSAVERS SEP COM | G24: DIRECT CREDIT | H24: 5450 | I24: =IF(H24>0,H24,"") -> 5450 | K24: 18157.66 | L24: =I24+J24 -> 5450 | M24: =K23+L24 -> 18157.66 | N24: =K24-M24 -> 0 | O24: REVENUE | P24: Income
A25: 23 | B25: SA24/25 | C25: FY25 | D25: 45434 | E25: Specsavers | F25: SPECSAVERS SEP COM | G25: DIRECT CREDIT | H25: 500 | I25: =IF(H25>0,H25,"") -> 500 | K25: 18657.66 | L25: =I25+J25 -> 500 | M25: =K24+L25 -> 18657.66 | N25: =K25-M25 -> 0 | O25: REVENUE | P25: Income
A26: 24 | B26: SA24/25 | C26: FY25 | D26: 45435 | E26: Tmchartered Limited | F26: Accounts | G26: FASTER PAYMENT | H26: -300 | J26: =IF(H26<0,H26,"") -> -300 | K26: 18357.66 | L26: =I26+J26 -> -300 | M26: =K25+L26 -> 18357.66 | N26: =K26-M26 -> 0 | O26: PROFESSIONAL_SERVICES | P26: Accountancy fee
A27: 25 | B27: SA24/25 | C27: FY25 | D27: 45439 | E27: RingGo | F27: RINGGO PARKING | G27: APPLE PAY | H27: -2.1 | J27: =IF(H27<0,H27,"") -> -2.1 | K27: 18355.56 | L27: =I27+J27 -> -2.1 | M27: =K26+L27 -> 18355.56 | N27: =K27-M27 -> 0 | O27: TRAVEL | P27: Travel
A28: 26 | B28: SA24/25 | C28: FY25 | D28: 45441 | E28: LOOKING GOOD OPTICIANS LIMITED T AS | F28: wadhurst | G28: FASTER PAYMENT | H28: 200 | I28: =IF(H28>0,H28,"") -> 200 | K28: 18555.56 | L28: =I28+J28 -> 200 | M28: =K27+L28 -> 18555.56 | N28: =K28-M28 -> 0 | O28: REVENUE | P28: Income
A29: 27 | B29: SA24/25 | C29: FY25 | D29: 45443 | E29: MiPermit | F29: MIPERMIT LTD | G29: APPLE PAY | H29: -1.1 | J29: =IF(H29<0,H29,"") -> -1.1 | K29: 18554.46 | L29: =I29+J29 -> -1.1 | M29: =K28+L29 -> 18554.46 | N29: =K29-M29 -> 0 | O29: TRAVEL | P29: Travel
A30: 28 | B30: SA24/25 | C30: FY25 | D30: 45443 | E30: MiPermit | F30: MIPERMIT LTD | G30: APPLE PAY | H30: -1 | J30: =IF(H30<0,H30,"") -> -1 | K30: 18553.46 | L30: =I30+J30 -> -1 | M30: =K29+L30 -> 18553.46 | N30: =K30-M30 -> 0 | O30: TRAVEL | P30: Travel
A31: 29 | B31: SA24/25 | C31: FY25 | D31: 45446 | E31: Barclays Current | F31: 208813 93228126 | G31: FASTER PAYMENT | H31: -700 | J31: =IF(H31<0,H31,"") -> -700 | K31: 17853.46 | L31: =I31+J31 -> -700 | M31: =K30+L31 -> 17853.46 | N31: =K31-M31 -> 0 | O31: DIRECTORS_WAGES | P31: Directors salary
A32: 30 | B32: SA24/25 | C32: FY25 | D32: 45446 | E32: Association Of Optometrists | F32: 87201 | G32: DIRECT DEBIT | H32: -72 | J32: =IF(H32<0,H32,"") -> -72 | K32: 17781.46 | L32: =I32+J32 -> -72 | M32: =K31+L32 -> 17781.46 | N32: =K32-M32 -> 0 | O32: PROFESSIONAL_SERVICES | P32: AOP
A33: 31 | B33: SA24/25 | C33: FY25 | D33: 45446 | E33: The College Of Optometrists | F33: DD003133 | G33: DIRECT DEBIT | H33: -127.09 | J33: =IF(H33<0,H33,"") -> -127.09 | K33: 17654.37 | L33: =I33+J33 -> -127.09 | M33: =K32+L33 -> 17654.37 | N33: =K33-M33 -> 0 | O33: PROFESSIONAL_SERVICES | P33: College
A34: 32 | B34: SA24/25 | C34: FY25 | D34: 45450 | E34: Specsavers | F34: SPECSAVERS SEP COM | G34: DIRECT CREDIT | H34: 3400 | I34: =IF(H34>0,H34,"") -> 3400 | K34: 21054.37 | L34: =I34+J34 -> 3400 | M34: =K33+L34 -> 21054.37 | N34: =K34-M34 -> 0 | O34: REVENUE | P34: Income
A35: 33 | B35: SA24/25 | C35: FY25 | D35: 45451 | E35: MiPermit | F35: MIPERMIT LTD | G35: APPLE PAY | H35: -1.1 | J35: =IF(H35<0,H35,"") -> -1.1 | K35: 21053.27 | L35: =I35+J35 -> -1.1 | M35: =K34+L35 -> 21053.27 | N35: =K35-M35 -> 0 | O35: TRAVEL | P35: Travel
A36: 34 | B36: SA24/25 | C36: FY25 | D36: 45451 | E36: MiPermit | F36: MIPERMIT LTD | G36: APPLE PAY | H36: -1 | J36: =IF(H36<0,H36,"") -> -1 | K36: 21052.27 | L36: =I36+J36 -> -1 | M36: =K35+L36 -> 21052.27 | N36: =K36-M36 -> 0 | O36: TRAVEL | P36: Travel
A37: 35 | B37: SA24/25 | C37: FY25 | D37: 45451 | E37: MiPermit | F37: MIPERMIT LTD | G37: APPLE PAY | H37: -1.1 | J37: =IF(H37<0,H37,"") -> -1.1 | K37: 21051.17 | L37: =I37+J37 -> -1.1 | M37: =K36+L37 -> 21051.17 | N37: =K37-M37 -> 0 | O37: TRAVEL | P37: Travel
A38: 36 | B38: SA24/25 | C38: FY25 | D38: 45451 | E38: MiPermit | F38: MIPERMIT LTD | G38: APPLE PAY | H38: -1.1 | J38: =IF(H38<0,H38,"") -> -1.1 | K38: 21050.07 | L38: =I38+J38 -> -1.1 | M38: =K37+L38 -> 21050.07 | N38: =K38-M38 -> 0 | O38: TRAVEL | P38: Travel
A39: 37 | B39: SA24/25 | C39: FY25 | D39: 45455 | E39: Specsavers | F39: SPECSAVERS SEP COM | G39: DIRECT CREDIT | H39: 3300 | I39: =IF(H39>0,H39,"") -> 3300 | K39: 24350.07 | L39: =I39+J39 -> 3300 | M39: =K38+L39 -> 24350.07 | N39: =K39-M39 -> 0 | O39: REVENUE | P39: Income
A40: 38 | B40: SA24/25 | C40: FY25 | D40: 45461 | E40: Tmchartered Limited | F40: Accounts MF | G40: FASTER PAYMENT | H40: -300 | J40: =IF(H40<0,H40,"") -> -300 | K40: 24050.07 | L40: =I40+J40 -> -300 | M40: =K39+L40 -> 24050.07 | N40: =K40-M40 -> 0 | O40: PROFESSIONAL_SERVICES | P40: Accountancy fee
A41: 39 | B41: SA24/25 | C41: FY25 | D41: 45470 | E41: LOOKING GOOD OPTICIANS LIMITED T AS | F41: wadhurst | G41: FASTER PAYMENT | H41: 700 | I41: =IF(H41>0,H41,"") -> 700 | K41: 24750.07 | L41: =I41+J41 -> 700 | M41: =K40+L41 -> 24750.07 | N41: =K41-M41 -> 0 | O41: REVENUE | P41: Income
A42: 40 | B42: SA24/25 | C42: FY25 | D42: 45471 | E42: Barclays Current | F42: Dividend | G42: FASTER PAYMENT | H42: -4000 | J42: =IF(H42<0,H42,"") -> -4000 | K42: 20750.07 | L42: =I42+J42 -> -4000 | M42: =K41+L42 -> 20750.07 | N42: =K42-M42 -> 0 | O42: DIVIDENDS | P42: Dividends
A43: 41 | B43: SA24/25 | C43: FY25 | D43: 45473 | E43: Hl | F43: WWW.HL.CO.UK | G43: ONLINE PAYMENT | H43: -750 | J43: =IF(H43<0,H43,"") -> -750 | K43: 20000.07 | L43: =I43+J43 -> -750 | M43: =K42+L43 -> 20000.07 | N43: =K43-M43 -> 0 | O43: STAFF | P43: SIPP
A44: 42 | B44: SA24/25 | C44: FY25 | D44: 45474 | E44: Association Of Optometrists | F44: 87201 | G44: DIRECT DEBIT | H44: -72 | J44: =IF(H44<0,H44,"") -> -72 | K44: 19928.07 | L44: =I44+J44 -> -72 | M44: =K43+L44 -> 19928.07 | N44: =K44-M44 -> 0 | O44: PROFESSIONAL_SERVICES | P44: AOP
A45: 43 | B45: SA24/25 | C45: FY25 | D45: 45474 | E45: Barclays Current | F45: 208813 93228126 | G45: FASTER PAYMENT | H45: -1000 | J45: =IF(H45<0,H45,"") -> -1000 | K45: 18928.07 | L45: =I45+J45 -> -1000 | M45: =K44+L45 -> 18928.07 | N45: =K45-M45 -> 0 | O45: DIRECTORS_WAGES | P45: Directors salary
A46: 44 | B46: SA24/25 | C46: FY25 | D46: 45477 | E46: WILKINSON LTD ZZ | F46: WILK SEV | G46: FASTER PAYMENT | H46: 450 | I46: =IF(H46>0,H46,"") -> 450 | K46: 19378.07 | L46: =I46+J46 -> 450 | M46: =K45+L46 -> 19378.07 | N46: =K46-M46 -> 0 | O46: REVENUE | P46: Income
A47: 45 | B47: SA24/25 | C47: FY25 | D47: 45478 | E47: Specsavers | F47: SPECSAVERS SEP COM | G47: DIRECT CREDIT | H47: 5043 | I47: =IF(H47>0,H47,"") -> 5043 | K47: 24421.07 | L47: =I47+J47 -> 5043 | M47: =K46+L47 -> 24421.07 | N47: =K47-M47 -> 0 | O47: REVENUE | P47: Income
A48: 46 | B48: SA24/25 | C48: FY25 | D48: 45478 | E48: Barclays Current | F48: Dividend | G48: FASTER PAYMENT | H48: -2000 | J48: =IF(H48<0,H48,"") -> -2000 | K48: 22421.07 | L48: =I48+J48 -> -2000 | M48: =K47+L48 -> 22421.07 | N48: =K48-M48 -> 0 | O48: DIVIDENDS | P48: Dividends
A49: 47 | B49: SA24/25 | C49: FY25 | D49: 45480 | E49: MiPermit | F49: MIPERMIT LTD | G49: APPLE PAY | H49: -1.1 | J49: =IF(H49<0,H49,"") -> -1.1 | K49: 22419.97 | L49: =I49+J49 -> -1.1 | M49: =K48+L49 -> 22419.97 | N49: =K49-M49 -> 0 | O49: TRAVEL | P49: Travel
A50: 48 | B50: SA24/25 | C50: FY25 | D50: 45485 | E50: Abbeyfield Ve Limi | F50: RG05570000565224 | G50: DIRECT CREDIT | H50: 375 | I50: =IF(H50>0,H50,"") -> 375 | K50: 22794.97 | L50: =I50+J50 -> 375 | M50: =K49+L50 -> 22794.97 | N50: =K50-M50 -> 0 | O50: REVENUE | P50: Income
A51: 49 | B51: SA24/25 | C51: FY25 | D51: 45490 | E51: MiPermit | F51: MIPERMIT LTD | G51: APPLE PAY | H51: -1.1 | J51: =IF(H51<0,H51,"") -> -1.1 | K51: 22793.87 | L51: =I51+J51 -> -1.1 | M51: =K50+L51 -> 22793.87 | N51: =K51-M51 -> 0 | O51: TRAVEL | P51: Travel
A52: 50 | B52: SA24/25 | C52: FY25 | D52: 45491 | E52: Uh Ecommerce Pay360 | F52: UNI OF HERTFORDSHIRE | G52: ONLINE PAYMENT | H52: -1400 | J52: =IF(H52<0,H52,"") -> -1400 | K52: 21393.87 | L52: =I52+J52 -> -1400 | M52: =K51+L52 -> 21393.87 | N52: =K52-M52 -> 0 | O52: PROFESSIONAL_SERVICES | P52: Univerisity fee?
A53: 51 | B53: SA24/25 | C53: FY25 | D53: 45491 | E53: MiPermit | F53: MIPERMIT LTD | G53: APPLE PAY | H53: -1.1 | J53: =IF(H53<0,H53,"") -> -1.1 | K53: 21392.77 | L53: =I53+J53 -> -1.1 | M53: =K52+L53 -> 21392.77 | N53: =K53-M53 -> 0 | O53: TRAVEL | P53: Travel
A54: 52 | B54: SA24/25 | C54: FY25 | D54: 45493 | E54: LOOKING GOOD OPTICIANS LIMITED T AS | F54: wadhurst | G54: FASTER PAYMENT | H54: 1100 | I54: =IF(H54>0,H54,"") -> 1100 | K54: 22492.77 | L54: =I54+J54 -> 1100 | M54: =K53+L54 -> 22492.77 | N54: =K54-M54 -> 0 | O54: REVENUE | P54: Income
A55: 53 | B55: SA24/25 | C55: FY25 | D55: 45497 | E55: Barclays Current | F55: Dividend | G55: FASTER PAYMENT | H55: -7500 | J55: =IF(H55<0,H55,"") -> -7500 | K55: 14992.77 | L55: =I55+J55 -> -7500 | M55: =K54+L55 -> 14992.77 | N55: =K55-M55 -> 0 | O55: DIVIDENDS | P55: Dividends
A56: 54 | B56: SA24/25 | C56: FY25 | D56: 45505 | E56: Barclays Current | F56: 208813 93228126 | G56: FASTER PAYMENT | H56: -1000 | J56: =IF(H56<0,H56,"") -> -1000 | K56: 13992.77 | L56: =I56+J56 -> -1000 | M56: =K55+L56 -> 13992.77 | N56: =K56-M56 -> 0 | O56: DIRECTORS_WAGES | P56: Directors salary
A57: 55 | B57: SA24/25 | C57: FY25 | D57: 45505 | E57: Association Of Optometrists | F57: 87201 | G57: DIRECT DEBIT | H57: -72 | J57: =IF(H57<0,H57,"") -> -72 | K57: 13920.77 | L57: =I57+J57 -> -72 | M57: =K56+L57 -> 13920.77 | N57: =K57-M57 -> 0 | O57: PROFESSIONAL_SERVICES | P57: AOP
A58: 56 | B58: SA24/25 | C58: FY25 | D58: 45511 | E58: Specsavers | F58: SPECSAVERS SEP COM | G58: DIRECT CREDIT | H58: 2350 | I58: =IF(H58>0,H58,"") -> 2350 | K58: 16270.77 | L58: =I58+J58 -> 2350 | M58: =K57+L58 -> 16270.77 | N58: =K58-M58 -> 0 | O58: REVENUE | P58: Income
A59: 57 | B59: SA24/25 | C59: FY25 | D59: 45512 | E59: RingGo | F59: RINGGO PARKING | G59: APPLE PAY | H59: -7 | J59: =IF(H59<0,H59,"") -> -7 | K59: 16263.77 | L59: =I59+J59 -> -7 | M59: =K58+L59 -> 16263.77 | N59: =K59-M59 -> 0 | O59: TRAVEL | P59: Travel
A60: 58 | B60: SA24/25 | C60: FY25 | D60: 45513 | E60: Specsavers | F60: SPECSAVERS SEP COM | G60: DIRECT CREDIT | H60: 2125 | I60: =IF(H60>0,H60,"") -> 2125 | K60: 18388.77 | L60: =I60+J60 -> 2125 | M60: =K59+L60 -> 18388.77 | N60: =K60-M60 -> 0 | O60: REVENUE | P60: Income
A61: 59 | B61: SA24/25 | C61: FY25 | D61: 45516 | E61: WILKINSON LTD ZZ | F61: WILK SEV | G61: FASTER PAYMENT | H61: 900 | I61: =IF(H61>0,H61,"") -> 900 | K61: 19288.77 | L61: =I61+J61 -> 900 | M61: =K60+L61 -> 19288.77 | N61: =K61-M61 -> 0 | O61: REVENUE | P61: Income
A62: 60 | B62: SA24/25 | C62: FY25 | D62: 45520 | E62: Specsavers | F62: SPECSAVERS SEP COM | G62: DIRECT CREDIT | H62: 430 | I62: =IF(H62>0,H62,"") -> 430 | K62: 19718.77 | L62: =I62+J62 -> 430 | M62: =K61+L62 -> 19718.77 | N62: =K62-M62 -> 0 | O62: REVENUE | P62: Income
A63: 61 | B63: SA24/25 | C63: FY25 | D63: 45522 | E63: MiPermit | F63: MIPERMIT LTD | G63: APPLE PAY | H63: -5.6 | J63: =IF(H63<0,H63,"") -> -5.6 | K63: 19713.17 | L63: =I63+J63 -> -5.6 | M63: =K62+L63 -> 19713.17 | N63: =K63-M63 -> 0 | O63: TRAVEL | P63: Travel
A64: 62 | B64: SA24/25 | C64: FY25 | D64: 45523 | E64: MiPermit | F64: MIPERMIT LTD | G64: APPLE PAY | H64: -5.6 | J64: =IF(H64<0,H64,"") -> -5.6 | K64: 19707.57 | L64: =I64+J64 -> -5.6 | M64: =K63+L64 -> 19707.57 | N64: =K64-M64 -> 0 | O64: TRAVEL | P64: Travel
A65: 63 | B65: SA24/25 | C65: FY25 | D65: 45525 | E65: MiPermit | F65: MIPERMIT LTD | G65: APPLE PAY | H65: -5.6 | J65: =IF(H65<0,H65,"") -> -5.6 | K65: 19701.97 | L65: =I65+J65 -> -5.6 | M65: =K64+L65 -> 19701.97 | N65: =K65-M65 -> 0 | O65: TRAVEL | P65: Travel
A66: 64 | B66: SA24/25 | C66: FY25 | D66: 45526 | E66: Hl | F66: WWW.HL.CO.UK | G66: ONLINE PAYMENT | H66: -750 | J66: =IF(H66<0,H66,"") -> -750 | K66: 18951.97 | L66: =I66+J66 -> -750 | M66: =K65+L66 -> 18951.97 | N66: =K66-M66 -> 0 | O66: STAFF | P66: SIPP
A67: 65 | B67: SA24/25 | C67: FY25 | D67: 45526 | E67: MiPermit | F67: MIPERMIT LTD | G67: APPLE PAY | H67: -5.6 | J67: =IF(H67<0,H67,"") -> -5.6 | K67: 18946.37 | L67: =I67+J67 -> -5.6 | M67: =K66+L67 -> 18946.37 | N67: =K67-M67 -> 0 | O67: TRAVEL | P67: Travel
A68: 66 | B68: SA24/25 | C68: FY25 | D68: 45529 | E68: MiPermit | F68: MIPERMIT LTD | G68: APPLE PAY | H68: -5.6 | J68: =IF(H68<0,H68,"") -> -5.6 | K68: 18940.77 | L68: =I68+J68 -> -5.6 | M68: =K67+L68 -> 18940.77 | N68: =K68-M68 -> 0 | O68: TRAVEL | P68: Travel
A69: 67 | B69: SA24/25 | C69: FY25 | D69: 45530 | E69: MiPermit | F69: MIPERMIT LTD | G69: APPLE PAY | H69: -5.1 | J69: =IF(H69<0,H69,"") -> -5.1 | K69: 18935.67 | L69: =I69+J69 -> -5.1 | M69: =K68+L69 -> 18935.67 | N69: =K69-M69 -> 0 | O69: TRAVEL | P69: Travel
A70: 68 | B70: SA24/25 | C70: FY25 | D70: 45533 | E70: LOOKING GOOD OPTICIANS LIMITED T AS | F70: wadhurst | G70: FASTER PAYMENT | H70: 1200 | I70: =IF(H70>0,H70,"") -> 1200 | K70: 20135.67 | L70: =I70+J70 -> 1200 | M70: =K69+L70 -> 20135.67 | N70: =K70-M70 -> 0 | O70: REVENUE | P70: Income
A71: 69 | B71: SA24/25 | C71: FY25 | D71: 45533 | E71: Barclays Current | F71: Dividend | G71: FASTER PAYMENT | H71: -2000 | J71: =IF(H71<0,H71,"") -> -2000 | K71: 18135.67 | L71: =I71+J71 -> -2000 | M71: =K70+L71 -> 18135.67 | N71: =K71-M71 -> 0 | O71: DIVIDENDS | P71: Dividends
A72: 70 | B72: SA24/25 | C72: FY25 | D72: 45537 | E72: Barclays Current | F72: 208813 93228126 | G72: FASTER PAYMENT | H72: -1000 | J72: =IF(H72<0,H72,"") -> -1000 | K72: 17135.67 | L72: =I72+J72 -> -1000 | M72: =K71+L72 -> 17135.67 | N72: =K72-M72 -> 0 | O72: DIRECTORS_WAGES | P72: Directors salary
A73: 71 | B73: SA24/25 | C73: FY25 | D73: 45537 | E73: Association Of Optometrists | F73: 87201 | G73: DIRECT DEBIT | H73: -72 | J73: =IF(H73<0,H73,"") -> -72 | K73: 17063.67 | L73: =I73+J73 -> -72 | M73: =K72+L73 -> 17063.67 | N73: =K73-M73 -> 0 | O73: PROFESSIONAL_SERVICES | P73: AOP
A74: 72 | B74: SA24/25 | C74: FY25 | D74: 45540 | E74: Lser Connect Ecom | F74: LSER CONNECT ECOM | G74: APPLE PAY | H74: -7 | J74: =IF(H74<0,H74,"") -> -7 | K74: 17056.67 | L74: =I74+J74 -> -7 | M74: =K73+L74 -> 17056.67 | N74: =K74-M74 -> 0 | O74: TRAVEL | P74: Travel
A75: 73 | B75: SA24/25 | C75: FY25 | D75: 45540 | E75: MiPermit | F75: MIPERMIT LTD | G75: APPLE PAY | H75: -2.1 | J75: =IF(H75<0,H75,"") -> -2.1 | K75: 17054.57 | L75: =I75+J75 -> -2.1 | M75: =K74+L75 -> 17054.57 | N75: =K75-M75 -> 0 | O75: TRAVEL | P75: Travel
A76: 74 | B76: SA24/25 | C76: FY25 | D76: 45541 | E76: Specsavers | F76: SPECSAVERS SEP COM | G76: DIRECT CREDIT | H76: 3825 | I76: =IF(H76>0,H76,"") -> 3825 | K76: 20879.57 | L76: =I76+J76 -> 3825 | M76: =K75+L76 -> 20879.57 | N76: =K76-M76 -> 0 | O76: REVENUE | P76: Income
A77: 75 | B77: SA24/25 | C77: FY25 | D77: 45543 | E77: MiPermit | F77: MIPERMIT LTD | G77: APPLE PAY | H77: -4.1 | J77: =IF(H77<0,H77,"") -> -4.1 | K77: 20875.47 | L77: =I77+J77 -> -4.1 | M77: =K76+L77 -> 20875.47 | N77: =K77-M77 -> 0 | O77: TRAVEL | P77: Travel
A78: 76 | B78: SA24/25 | C78: FY25 | D78: 45543 | E78: MiPermit | F78: MIPERMIT LTD | G78: APPLE PAY | H78: -5.1 | J78: =IF(H78<0,H78,"") -> -5.1 | K78: 20870.37 | L78: =I78+J78 -> -5.1 | M78: =K77+L78 -> 20870.37 | N78: =K78-M78 -> 0 | O78: TRAVEL | P78: Travel
A79: 77 | B79: SA24/25 | C79: FY25 | D79: 45544 | E79: WILKINSON LTD ZZ | F79: WILK SEV | G79: FASTER PAYMENT | H79: 900 | I79: =IF(H79>0,H79,"") -> 900 | K79: 21770.37 | L79: =I79+J79 -> 900 | M79: =K78+L79 -> 21770.37 | N79: =K79-M79 -> 0 | O79: REVENUE | P79: Income
A80: 78 | B80: SA24/25 | C80: FY25 | D80: 45546 | E80: Specsavers | F80: SPECSAVERS SEP COM | G80: DIRECT CREDIT | H80: 1826 | I80: =IF(H80>0,H80,"") -> 1826 | K80: 23596.37 | L80: =I80+J80 -> 1826 | M80: =K79+L80 -> 23596.37 | N80: =K80-M80 -> 0 | O80: REVENUE | P80: Income
A81: 79 | B81: SA24/25 | C81: FY25 | D81: 45548 | E81: Abbeyfield Ve Limi | F81: RG05570000805124 | G81: DIRECT CREDIT | H81: 375 | I81: =IF(H81>0,H81,"") -> 375 | K81: 23971.37 | L81: =I81+J81 -> 375 | M81: =K80+L81 -> 23971.37 | N81: =K81-M81 -> 0 | O81: REVENUE | P81: Income
A82: 80 | B82: SA24/25 | C82: FY25 | D82: 45548 | E82: MiPermit | F82: MIPERMIT LTD | G82: APPLE PAY | H82: -5.6 | J82: =IF(H82<0,H82,"") -> -5.6 | K82: 23965.77 | L82: =I82+J82 -> -5.6 | M82: =K81+L82 -> 23965.77 | N82: =K82-M82 -> 0 | O82: TRAVEL | P82: Travel
A83: 81 | B83: SA24/25 | C83: FY25 | D83: 45551 | E83: MiPermit | F83: MIPERMIT LTD | G83: APPLE PAY | H83: -4.1 | J83: =IF(H83<0,H83,"") -> -4.1 | K83: 23961.67 | L83: =I83+J83 -> -4.1 | M83: =K82+L83 -> 23961.67 | N83: =K83-M83 -> 0 | O83: TRAVEL | P83: Travel
A84: 82 | B84: SA24/25 | C84: FY25 | D84: 45551 | E84: MiPermit | F84: MIPERMIT LTD | G84: APPLE PAY | H84: -5.1 | J84: =IF(H84<0,H84,"") -> -5.1 | K84: 23956.57 | L84: =I84+J84 -> -5.1 | M84: =K83+L84 -> 23956.57 | N84: =K84-M84 -> 0 | O84: TRAVEL | P84: Travel
A85: 83 | B85: SA24/25 | C85: FY25 | D85: 45555 | E85: MiPermit | F85: MIPERMIT LTD | G85: APPLE PAY | H85: -1.6 | J85: =IF(H85<0,H85,"") -> -1.6 | K85: 23954.97 | L85: =I85+J85 -> -1.6 | M85: =K84+L85 -> 23954.97 | N85: =K85-M85 -> 0 | O85: TRAVEL | P85: Travel
A86: 84 | B86: SA24/25 | C86: FY25 | D86: 45559 | E86: LOOKING GOOD OPTICIANS LIMITED T AS | F86: wadhurst | G86: FASTER PAYMENT | H86: 200 | I86: =IF(H86>0,H86,"") -> 200 | K86: 24154.97 | L86: =I86+J86 -> 200 | M86: =K85+L86 -> 24154.97 | N86: =K86-M86 -> 0 | O86: REVENUE | P86: Income
A87: 85 | B87: SA24/25 | C87: FY25 | D87: 45563 | E87: Tmchartered Limited | F87: Accounts MF | G87: FASTER PAYMENT | H87: -48 | J87: =IF(H87<0,H87,"") -> -48 | K87: 24106.97 | L87: =I87+J87 -> -48 | M87: =K86+L87 -> 24106.97 | N87: =K87-M87 -> 0 | O87: PROFESSIONAL_SERVICES | P87: Accountancy fee
A88: 86 | B88: SA24/25 | C88: FY25 | D88: 45563 | E88: Hl | F88: WWW.HL.CO.UK | G88: ONLINE PAYMENT | H88: -1500 | J88: =IF(H88<0,H88,"") -> -1500 | K88: 22606.97 | L88: =I88+J88 -> -1500 | M88: =K87+L88 -> 22606.97 | N88: =K88-M88 -> 0 | O88: STAFF | P88: SIPP
A89: 87 | B89: SA24/25 | C89: FY25 | D89: 45565 | E89: MiPermit | F89: MIPERMIT LTD | G89: APPLE PAY | H89: -5.6 | J89: =IF(H89<0,H89,"") -> -5.6 | K89: 22601.37 | L89: =I89+J89 -> -5.6 | M89: =K88+L89 -> 22601.37 | N89: =K89-M89 -> 0 | O89: TRAVEL | P89: Travel
A90: 88 | B90: SA24/25 | C90: FY25 | D90: 45566 | E90: The College Of Optometrists | F90: DD003133 | G90: DIRECT DEBIT | H90: -316 | J90: =IF(H90<0,H90,"") -> -316 | K90: 22285.37 | L90: =I90+J90 -> -316 | M90: =K89+L90 -> 22285.37 | N90: =K90-M90 -> 0 | O90: PROFESSIONAL_SERVICES | P90: College
A91: 89 | B91: SA24/25 | C91: FY25 | D91: 45566 | E91: Association Of Optometrists | F91: 87201 | G91: DIRECT DEBIT | H91: -72 | J91: =IF(H91<0,H91,"") -> -72 | K91: 22213.37 | L91: =I91+J91 -> -72 | M91: =K90+L91 -> 22213.37 | N91: =K91-M91 -> 0 | O91: PROFESSIONAL_SERVICES | P91: AOP
A92: 90 | B92: SA24/25 | C92: FY25 | D92: 45566 | E92: Barclays Current | F92: 208813 93228126 | G92: FASTER PAYMENT | H92: -1000 | J92: =IF(H92<0,H92,"") -> -1000 | K92: 21213.37 | L92: =I92+J92 -> -1000 | M92: =K91+L92 -> 21213.37 | N92: =K92-M92 -> 0 | O92: DIRECTORS_WAGES | P92: Directors salary
A93: 91 | B93: SA24/25 | C93: FY25 | D93: 45573 | E93: MiPermit | F93: MIPERMIT LTD | G93: APPLE PAY | H93: -2.1 | J93: =IF(H93<0,H93,"") -> -2.1 | K93: 21211.27 | L93: =I93+J93 -> -2.1 | M93: =K92+L93 -> 21211.27 | N93: =K93-M93 -> 0 | O93: TRAVEL | P93: Travel
A94: 92 | B94: SA24/25 | C94: FY25 | D94: 45574 | E94: Specsavers | F94: SPECSAVERS SEP COM | G94: DIRECT CREDIT | H94: 3400 | I94: =IF(H94>0,H94,"") -> 3400 | K94: 24611.27 | L94: =I94+J94 -> 3400 | M94: =K93+L94 -> 24611.27 | N94: =K94-M94 -> 0 | O94: REVENUE | P94: Income
A95: 93 | B95: SA24/25 | C95: FY25 | D95: 45574 | E95: Barclays Current | F95: Dividend | G95: FASTER PAYMENT | H95: -3000 | J95: =IF(H95<0,H95,"") -> -3000 | K95: 21611.27 | L95: =I95+J95 -> -3000 | M95: =K94+L95 -> 21611.27 | N95: =K95-M95 -> 0 | O95: DIVIDENDS | P95: Dividends
A96: 94 | B96: SA24/25 | C96: FY25 | D96: 45579 | E96: Specsavers | F96: SPECSAVERS SEP COM | G96: DIRECT CREDIT | H96: 1275 | I96: =IF(H96>0,H96,"") -> 1275 | K96: 22886.27 | L96: =I96+J96 -> 1275 | M96: =K95+L96 -> 22886.27 | N96: =K96-M96 -> 0 | O96: REVENUE | P96: Income
A97: 95 | B97: SA24/25 | C97: FY25 | D97: 45579 | E97: WILKINSON LTD ZZ | F97: WILK SEV | G97: FASTER PAYMENT | H97: 900 | I97: =IF(H97>0,H97,"") -> 900 | K97: 23786.27 | L97: =I97+J97 -> 900 | M97: =K96+L97 -> 23786.27 | N97: =K97-M97 -> 0 | O97: REVENUE | P97: Income
A98: 96 | B98: SA24/25 | C98: FY25 | D98: 45580 | E98: The AA | F98: AA MOTOR INSURANCE | G98: ONLINE PAYMENT | H98: -428.77 | J98: =IF(H98<0,H98,"") -> -428.77 | K98: 23357.5 | L98: =I98+J98 -> -428.77 | M98: =K97+L98 -> 23357.5 | N98: =K98-M98 -> 0 | O98: VEHICLES | P98: DLA
A99: 97 | B99: SA24/25 | C99: FY25 | D99: 45581 | E99: Nando's | F99: NANDOS.CO.UK | G99: APPLE PAY | H99: -16.2 | J99: =IF(H99<0,H99,"") -> -16.2 | K99: 23341.3 | L99: =I99+J99 -> -16.2 | M99: =K98+L99 -> 23341.3 | N99: =K99-M99 -> 0 | O99: FOOD_AND_DRINK | P99: Lunch
A100: 98 | B100: SA24/25 | C100: FY25 | D100: 45582 | E100: MiPermit | F100: MIPERMIT LTD | G100: APPLE PAY | H100: -6.1 | J100: =IF(H100<0,H100,"") -> -6.1 | K100: 23335.2 | L100: =I100+J100 -> -6.1 | M100: =K99+L100 -> 23335.2 | N100: =K100-M100 -> 0 | O100: TRAVEL | P100: Travel
...

Sheet Analysis
A3: Sum of NET | B3: Column Labels
A4: Row Labels | B4: FY24 | C4: FY25
A5: AOP | B5: =SUMIFS('RAW 2025'!$L:$L,'RAW 2025'!$C:$C,$B$4,'RAW 2025'!$P:$P,$A5) -> -73 | C5: =SUMIFS('RAW 2025'!$L:$L,'RAW 2025'!$C:$C,$C$4,'RAW 2025'!$P:$P,$A5) -> -1383
A6: Accountancy | B6: =SUMIFS('RAW 2025'!$L:$L,'RAW 2025'!$C:$C,$B$4,'RAW 2025'!$P:$P,$A6) -> 0 | C6: =SUMIFS('RAW 2025'!$L:$L,'RAW 2025'!$C:$C,$C$4,'RAW 2025'!$P:$P,$A6) -> -634
A7: Accountancy fee | B7: =SUMIFS('RAW 2025'!$L:$L,'RAW 2025'!$C:$C,$B$4,'RAW 2025'!$P:$P,$A7) -> 0 | C7: =SUMIFS('RAW 2025'!$L:$L,'RAW 2025'!$C:$C,$C$4,'RAW 2025'!$P:$P,$A7) -> -1016
A8: Car insurance | B8: =SUMIFS('RAW 2025'!$L:$L,'RAW 2025'!$C:$C,$B$4,'RAW 2025'!$P:$P,$A8) -> 0 | C8: =SUMIFS('RAW 2025'!$L:$L,'RAW 2025'!$C:$C,$C$4,'RAW 2025'!$P:$P,$A8) -> 193.25
A9: College | B9: =SUMIFS('RAW 2025'!$L:$L,'RAW 2025'!$C:$C,$B$4,'RAW 2025'!$P:$P,$A9) -> 0 | C9: =SUMIFS('RAW 2025'!$L:$L,'RAW 2025'!$C:$C,$C$4,'RAW 2025'!$P:$P,$A9) -> -443.09
A10: DBS | B10: =SUMIFS('RAW 2025'!$L:$L,'RAW 2025'!$C:$C,$B$4,'RAW 2025'!$P:$P,$A10) -> 0 | C10: =SUMIFS('RAW 2025'!$L:$L,'RAW 2025'!$C:$C,$C$4,'RAW 2025'!$P:$P,$A10) -> -16
A11: DLA | B11: =SUMIFS('RAW 2025'!$L:$L,'RAW 2025'!$C:$C,$B$4,'RAW 2025'!$P:$P,$A11) -> 0 | C11: =SUMIFS('RAW 2025'!$L:$L,'RAW 2025'!$C:$C,$C$4,'RAW 2025'!$P:$P,$A11) -> -428.77
A12: Dinner | B12: =SUMIFS('RAW 2025'!$L:$L,'RAW 2025'!$C:$C,$B$4,'RAW 2025'!$P:$P,$A12) -> 0 | C12: =SUMIFS('RAW 2025'!$L:$L,'RAW 2025'!$C:$C,$C$4,'RAW 2025'!$P:$P,$A12) -> -226.24
A13: Director's Salary | B13: =SUMIFS('RAW 2025'!$L:$L,'RAW 2025'!$C:$C,$B$4,'RAW 2025'!$P:$P,$A13) -> -1000 | C13: =SUMIFS('RAW 2025'!$L:$L,'RAW 2025'!$C:$C,$C$4,'RAW 2025'!$P:$P,$A13) -> -49250
A14: Directors salary | B14: =SUMIFS('RAW 2025'!$L:$L,'RAW 2025'!$C:$C,$B$4,'RAW 2025'!$P:$P,$A14) -> 0 | C14: =SUMIFS('RAW 2025'!$L:$L,'RAW 2025'!$C:$C,$C$4,'RAW 2025'!$P:$P,$A14) -> -11100
A15: Dividends | B15: =SUMIFS('RAW 2025'!$L:$L,'RAW 2025'!$C:$C,$B$4,'RAW 2025'!$P:$P,$A15) -> 0 | C15: =SUMIFS('RAW 2025'!$L:$L,'RAW 2025'!$C:$C,$C$4,'RAW 2025'!$P:$P,$A15) -> -40370
A16: Entertainment | B16: =SUMIFS('RAW 2025'!$L:$L,'RAW 2025'!$C:$C,$B$4,'RAW 2025'!$P:$P,$A16) -> 0 | C16: =SUMIFS('RAW 2025'!$L:$L,'RAW 2025'!$C:$C,$C$4,'RAW 2025'!$P:$P,$A16) -> -57.4
... A33: Univerisity fee? | B33: =SUMIFS('RAW 2025'!$L:$L,'RAW 2025'!$C:$C,$B$4,'RAW 2025'!$P:$P,$A33) -> 0 | C33: =SUMIFS('RAW 2025'!$L:$L,'RAW 2025'!$C:$C,$C$4,'RAW 2025'!$P:$P,$A33) -> -1400
A34: Grand Total | B34: =SUM(B5:B33) -> -1073 | C34: =SUM(C5:C33) -> 19070.7
